MANIFEST.in
README.md
setup.cfg
setup.py
textgenrnn/AttentionWeightedAverage.py
textgenrnn/__init__.py
textgenrnn/model.py
textgenrnn/textgenrnn.py
textgenrnn/textgenrnn_vocab.json
textgenrnn/textgenrnn_weights.hdf5
textgenrnn.egg-info/PKG-INFO
textgenrnn.egg-info/SOURCES.txt
textgenrnn.egg-info/dependency_links.txt
textgenrnn.egg-info/requires.txt
textgenrnn.egg-info/top_level.txt