Metadata-Version: 1.0
Name: textgenrnn
Version: 1.0
Summary: Pretrained character-based neural network for easily generating text.
Home-page: https://github.com/minimaxir/textgenrnn
Author: Max Woolf
Author-email: max@minimaxir.com
License: MIT
Keywords: deep learning,tensorflow,keras,text generation
Platform: UNKNOWN
